hvpdb_admin/__init__.py
hvpdb_admin-0.1.0.dist-info/METADATA
hvpdb_admin-0.1.0.dist-info/WHEEL
hvpdb_admin-0.1.0.dist-info/entry_points.txt
hvpdb_admin-0.1.0.dist-info/top_level.txt
hvpdb_admin-0.1.0.dist-info/RECORD
