Metadata-Version: 2.4
Name: hvpdb-admin
Version: 0.1.0
Summary: Admin & Audit Tools for HVPDB
Requires-Dist: hvpdb
Dynamic: requires-dist
Dynamic: summary
